error_handler_diploma/__init__.py
error_handler_diploma/error_handler.py
error_handler_diploma/test.py
error_handler_diploma-0.0.4.dist-info/METADATA
error_handler_diploma-0.0.4.dist-info/WHEEL
error_handler_diploma-0.0.4.dist-info/top_level.txt
error_handler_diploma-0.0.4.dist-info/RECORD
