Metadata-Version: 2.1
Name: error_handler_diploma
Version: 0.0.4
Summary: Error handling library
Author: Vladyslava Rozhkovan
Keywords: python,error handling,library,diploma project
Classifier: Development Status :: 3 - Alpha
Classifier: Intended Audience :: Education
Classifier: Programming Language :: Python :: 2
Classifier: Programming Language :: Python :: 3
Classifier: Operating System :: MacOS :: MacOS X
Classifier: Operating System :: Microsoft :: Windows
